core/__init__.py
core/main.py
pysend_cli-1.0.0.dist-info/LICENSE
pysend_cli-1.0.0.dist-info/METADATA
pysend_cli-1.0.0.dist-info/WHEEL
pysend_cli-1.0.0.dist-info/entry_points.txt
pysend_cli-1.0.0.dist-info/top_level.txt
pysend_cli-1.0.0.dist-info/RECORD
