Metadata-Version: 2.1
Name: pysend-cli
Version: 1.0.0
Summary: A simple command-line tool for sending emails to yourself
Home-page: https://github.com/jacksonet00/pysend
Author: jackson ⁖
Author-email: workwithjacksontaylor@gmail.com
Classifier: Programming Language :: Python :: 3
Classifier: License :: OSI Approved :: MIT License
Classifier: Operating System :: OS Independent
Requires-Python: >=3.6
License-File: LICENSE
